edi_parser
