Metadata-Version: 2.4
Name: bots-edi-parser
Version: 1.1.0
Summary: Standalone EDI parser extracted from Bots EDI Translator supporting EDIFACT, X12, and more
Home-page: https://github.com/yourusername/edi-parser
Author: Extracted from Bots EDI Translator
Author-email: 
License: GPL-3.0
Project-URL: Homepage, https://github.com/yourusername/edi-parser
Project-URL: Documentation, https://github.com/yourusername/edi-parser#readme
Project-URL: Repository, https://github.com/yourusername/edi-parser
Project-URL: Issues, https://github.com/yourusername/edi-parser/issues
Keywords: edi,edifact,x12,parser,healthcare,837,835,claims,remittance
Classifier: Development Status :: 4 - Beta
Classifier: Intended Audience :: Developers
Classifier: Intended Audience :: Healthcare Industry
Classifier: License :: OSI Approved :: GNU General Public License v3 (GPLv3)
Classifier: Programming Language :: Python :: 3
Classifier: Programming Language :: Python :: 3.9
Classifier: Programming Language :: Python :: 3.10
Classifier: Programming Language :: Python :: 3.11
Classifier: Programming Language :: Python :: 3.12
Classifier: Programming Language :: Python :: 3.13
Classifier: Topic :: Software Development :: Libraries :: Python Modules
Classifier: Topic :: Office/Business :: Financial
Classifier: Topic :: Text Processing
Requires-Python: >=3.7
Provides-Extra: dev
Requires-Dist: pytest>=7.0; extra == "dev"
Requires-Dist: black>=23.0; extra == "dev"
Requires-Dist: flake8>=6.0; extra == "dev"
Dynamic: home-page
Dynamic: requires-python
